maek/__init__.py
maek/__main__.py
maek/maek.py
maek/util.py
maek/version.py
maek-0.1.3.dist-info/METADATA
maek-0.1.3.dist-info/WHEEL
maek-0.1.3.dist-info/entry_points.txt
maek-0.1.3.dist-info/top_level.txt
maek-0.1.3.dist-info/zip-safe
maek-0.1.3.dist-info/RECORD
