Metadata-Version: 2.1
Name: maek
Version: 0.1.3
Summary: Command-line makefile replacement
Home-page: https://github.com/slightlynybbled/maek
Author: Jason R. Jones
Author-email: slightlynybbled@gmail.com
License: MIT
Keywords: c build make
Platform: UNKNOWN
Classifier: Development Status :: 4 - Beta
Classifier: Programming Language :: Python :: 3
Classifier: Programming Language :: Python :: 3.5
Classifier: Programming Language :: Python :: 3.6
Classifier: Programming Language :: Python :: 3.7
Classifier: Natural Language :: English
Requires-Dist: click (>=6.7)
Requires-Dist: coloredlogs (>=10.0)
Requires-Dist: tqdm (>=4.2)
Requires-Dist: pyyaml (>=3.1)
